quickassert/GenericAssertion.py
quickassert/NoAssertion.py
quickassert/__init__.py
quickassert-0.0.1.dist-info/METADATA
quickassert-0.0.1.dist-info/WHEEL
quickassert-0.0.1.dist-info/RECORD
