Metadata-Version: 2.1
Name: quickassert
Version: 0.0.1
Summary: Creates assertion administor (access) on relatively small prodjects, in order to save time used in raising and writing exceptions. It generate automatically a one-pattern exception.
Project-URL: Homepage, https://github.com/FLBPeriat/quickassert
Project-URL: Bug Tracker, https://github.com/FLBPeriat/quickassert/issues
Author-email: "F.L.B Périat" <florent.periat@gmail.com>
Classifier: License :: OSI Approved :: MIT License
Classifier: Operating System :: OS Independent
Classifier: Programming Language :: Python :: 3
Requires-Python: >=3.9
